<?xml version="1.0" encoding="UTF-8"?>
<Export generator="Cache" version="25" zv="Cache for Windows (x86-32) 2015.1 (Build 429U)" ts="2015-08-06 14:03:32">
<Document name="habrAnalytics-General-authorsViews.dashboard.DFI">
<dashboard xmlns="http://www.intersystems.com/deepsee/library" name="authorsViews" folderName="habrAnalytics/General" title="" description="" keywords="" owner="" shared="true" public="true" locked="false" resource="" timeCreated="2015-08-05T14:23:18.578Z" createdBy="UnknownUser" category="" bookCover="" scheme="" worklistCount="0" snapTo="true" snapGrid="true" gridRows="10" gridCols="10" canResize="true" canModify="true" showTitleBar="true" companyName="" companyLogo="" companyStyle="">
  <widget name="w1" type="pivot" subtype="columnChartStacked" subtypeClass="barChart" title="" dataSource="habrAnalytics/authorsViews.pivot" dataLink="" drillDownDataSource="" width="200" height="200" sidebarContent="" showSidebar="false" sidebarWidth="" maximized="false" homeRowL="0" homeColL="0" colSpanL="6" rowSpanL="6" showToolbar="true" theme="" dataColorList="">
    <control name="" action="applyFilter" target="" targetProperty="[dateOfPublication].[H1].[dateOfPublication]" location="widget" type="auto" controlClass="" label="Год публикации" title="" value="&amp;[2015]" text="" readOnly="false" valueList="" displayList="" activeWhen=""></control>
  </widget>
</dashboard>
</Document></Export>
